gguf_llama/__init__.py
gguf_llama/gguf_llama.py
gguf_llama-0.0.18.dist-info/METADATA
gguf_llama-0.0.18.dist-info/WHEEL
gguf_llama-0.0.18.dist-info/top_level.txt
gguf_llama-0.0.18.dist-info/RECORD
