Metadata-Version: 2.1
Name: gguf_llama
Version: 0.0.18
Summary: Wrapper for simplified use of Llama2 GGUF quantized models.
Home-page: https://github.com/laelhalawani/gguf_llama
Author: Łael Al-Halawani
Author-email: laelhalawani@gmail.com
Keywords: llama,gguf,quantized models,llama gguf,cpu inference
Classifier: Development Status :: 3 - Alpha
Classifier: Intended Audience :: Developers
Classifier: Intended Audience :: Education
Classifier: Intended Audience :: Information Technology
Classifier: License :: Free for non-commercial use
Classifier: Natural Language :: English
Classifier: Operating System :: OS Independent
Classifier: Programming Language :: Python :: 3
Classifier: Topic :: Scientific/Engineering :: Artificial Intelligence
Requires-Dist: util-helper ==0.0.5
Requires-Dist: llama-cpp-python >=0.2.26
